openvino2onnx/__init__.py
openvino2onnx/__main__.py
openvino2onnx/checker.py
openvino2onnx/graph.py
openvino2onnx/logger.py
openvino2onnx/pass_manager.py
openvino2onnx/py.typed
openvino2onnx/traits.py
openvino2onnx/utils.py
openvino2onnx/domain/README.md
openvino2onnx/domain/__init__.py
openvino2onnx/domain/intel/__init__.py
openvino2onnx/domain/intel/openvino/__init__.py
openvino2onnx/domain/intel/openvino/utils.py
openvino2onnx/domain/intel/openvino/xml_frontend.py
openvino2onnx/domain/intel/openvino/ir/__init__.py
openvino2onnx/domain/intel/openvino/ir/ir11.py
openvino2onnx/domain/intel/openvino/ir/mapping.py
openvino2onnx/domain/intel/openvino/passes/__init__.py
openvino2onnx/domain/intel/openvino/passes/eliminate_useless_floor.py
openvino2onnx/domain/intel/openvino/passes/shapeof_to_constant.py
openvino2onnx/domain/intel/openvino/passes/op/__init__.py
openvino2onnx/domain/intel/openvino/passes/op/avgpool.py
openvino2onnx/domain/intel/openvino/passes/op/batch_norm_inference.py
openvino2onnx/domain/intel/openvino/passes/op/broadcast.py
openvino2onnx/domain/intel/openvino/passes/op/clamp.py
openvino2onnx/domain/intel/openvino/passes/op/concat.py
openvino2onnx/domain/intel/openvino/passes/op/constant.py
openvino2onnx/domain/intel/openvino/passes/op/convert.py
openvino2onnx/domain/intel/openvino/passes/op/convolution.py
openvino2onnx/domain/intel/openvino/passes/op/convolution_backprop_data.py
openvino2onnx/domain/intel/openvino/passes/op/depth_to_space.py
openvino2onnx/domain/intel/openvino/passes/op/divide.py
openvino2onnx/domain/intel/openvino/passes/op/fake_quantize.py
openvino2onnx/domain/intel/openvino/passes/op/floormod.py
openvino2onnx/domain/intel/openvino/passes/op/gather.py
openvino2onnx/domain/intel/openvino/passes/op/gather_elements.py
openvino2onnx/domain/intel/openvino/passes/op/gather_nd.py
openvino2onnx/domain/intel/openvino/passes/op/greater_equal.py
openvino2onnx/domain/intel/openvino/passes/op/group_normalization.py
openvino2onnx-1.1.0.dist-info/entry_points.txt
openvino2onnx-1.1.0.dist-info/licenses/LICENSE
openvino2onnx-1.1.0.dist-info/WHEEL
openvino2onnx-1.1.0.dist-info/METADATA
openvino2onnx-1.1.0.dist-info/RECORD
