Metadata-Version: 2.4
Name: openvino2onnx
Version: 1.1.0
Summary: An Open Neural Network Exchange (ONNX) Optimization and Transformation Tool.
Author-email: Wenyi Tang <wenyitang@outlook.com>
Requires-Python: >=3.11
Classifier: License :: OSI Approved :: Apache Software License
Classifier: Topic :: Scientific/Engineering :: Artificial Intelligence
Classifier: Topic :: Software Development
License-File: LICENSE
Requires-Dist: onnx>=1.17.0
Requires-Dist: networkx
Requires-Dist: numpy<2.2.0
Requires-Dist: tabulate
Requires-Dist: colorlog>=6.9.0
Requires-Dist: termcolor>=3.1.0
Requires-Dist: onnxoptimizer ; extra == "test"
Requires-Dist: onnxruntime ; extra == "test"
Requires-Dist: onnxsim ; extra == "test"
Requires-Dist: openvino>=2025.0.0 ; extra == "test"
Requires-Dist: pre-commit ; extra == "test"
Requires-Dist: pytest ; extra == "test"
Requires-Dist: pytest-cov ; extra == "test"
Requires-Dist: pooch ; extra == "test"
Project-URL: Docs, https://loseall.github.io/openvino2onnx
Project-URL: Home, https://github.com/LoSealL/openvino2onnx
Provides-Extra: test
